rfb_config_tool/__init__.py
rfb_config_tool/__version__.py
rfb_config_tool/sys_conf.py
rfb_config_tool-0.0.2.dist-info/LICENSE.txt
rfb_config_tool-0.0.2.dist-info/METADATA
rfb_config_tool-0.0.2.dist-info/WHEEL
rfb_config_tool-0.0.2.dist-info/top_level.txt
rfb_config_tool-0.0.2.dist-info/RECORD
