Metadata-Version: 2.1
Name: rfb_config_tool
Version: 0.0.2
Summary: Toolchain used to read configuration file by section.
Author-email: Javier Sanz <javiersanzmoline@gmail.com>, Raldea <r.aldea.csic+pypi@gmail.com>, Marius Crisan <mariuscrsn+pypi@gmail.com>, Pablo Pastor <pastorpflores+pypi@gmail.com>, Luis Roche <luis.roche@hotmail.com>
Maintainer-email: Javier Sanz <javiersanzmoline@gmail.com>, Raldea <r.aldea.csic+pypi@gmail.com>
License: GNU GENERAL PUBLIC LICENSE
Project-URL: Homepage, https://github.com/WattRex/System-Tools
Project-URL: Bug Reports, https://github.com/WattRex/System-Tools/issues
Project-URL: Bug Tracker, https://github.com/WattRex/System-Tools/issues
Project-URL: Source, https://github.com/WattRex/System-Tools/tree/develop/code/sys_conf
Project-URL: Funding, https://donate.pypi.org
Keywords: yaml,configuration
Classifier: Development Status :: 3 - Alpha
Classifier: Topic :: Software Development :: Embedded Systems
Classifier: Operating System :: OS Independent
Classifier: License :: OSI Approved :: GNU Affero General Public License v3
Classifier: Programming Language :: Python :: 3
Classifier: Programming Language :: Python :: 3.7
Classifier: Programming Language :: Python :: 3.8
Classifier: Programming Language :: Python :: 3.9
Classifier: Programming Language :: Python :: 3.10
Classifier: Programming Language :: Python :: 3.11
Classifier: Programming Language :: Python :: 3 :: Only
Requires-Python: >=3.7
License-File: LICENSE.txt
Requires-Dist: PyYAML >=6.0.1
Requires-Dist: rfb-logger-tool >=0.0.1
